ogr/__init__.py
ogr/ampl/.gitignore
ogr/ampl/__init__.py
ogr/ampl/ogr.dat
ogr/ampl/ogr.mod
ogr/ampl/ogr.run
ogr/exceptions.py
ogr/generation.py
ogr/models.py
ogr/ruler.py
ogr/scripts.py
ogr/solvers.py
ogr/tests/__init__.py
ogr/tests/test_ogr.py
ogr/utils.py
ogr_main.py
ogr_py-0.1.3.dist-info/METADATA
ogr_py-0.1.3.dist-info/WHEEL
ogr_py-0.1.3.dist-info/entry_points.txt
ogr_py-0.1.3.dist-info/RECORD
